ams_rw_stdf/__init__.py
ams_rw_stdf/_ams_rw_stdf_writer_state.py
ams_rw_stdf/_opener_collection.py
ams_rw_stdf/blinder.py
ams_rw_stdf/closestdf.py
ams_rw_stdf/convert.py
ams_rw_stdf/simulator.py
ams_rw_stdf/stdfanalyser.py
ams_rw_stdf/stdfrenamer.py
ams_rw_stdf/version.py
ams_rw_stdf_writer/__init__.py
stdf_tamer-1.0.44.dist-info/METADATA
stdf_tamer-1.0.44.dist-info/WHEEL
stdf_tamer-1.0.44.dist-info/entry_points.txt
stdf_tamer-1.0.44.dist-info/licenses/LICENSE.txt
stdf_tamer-1.0.44.dist-info/RECORD
