Metadata-Version: 2.1
Name: stdf-tamer
Version: 1.0.44
Summary: a stdf reader/writer/analyser/converter and robotframework library
Keywords: STDF,ATE
Author: Labor DC jona
Author-Email: Franz Haas <franz.haas@ams-osram.com>, Roman Steiner <roman.steiner@ams-osram.com>
License: apache 2.0
Project-URL: Homepage, https://gittf.ams-osram.info/labor-rapperswil-jona/ams-tamer
Project-URL: Repository, https://gittf.ams-osram.info/labor-rapperswil-jona/ams-tamer
Project-URL: Documentation, https://labor-rapperswil-jona.git-pages.ams-osram.info/ams-tamer/index.html
Requires-Python: >=3.10.0
Requires-Dist: construct
Requires-Dist: docopt
Requires-Dist: rich
Requires-Dist: toml>=0.10.2
Requires-Dist: robotframework>=6.1.1; extra == "robotframework-bare"
Requires-Dist: pyarrow>=0.18.15; python_version >= "3.8" and extra == "robotframework-bare"
Requires-Dist: fastexcel; extra == "robotframework-bare"
Requires-Dist: XlsxWriter; extra == "robotframework-bare"
Requires-Dist: pyarrow>=0.18.15; python_version >= "3.8" and extra == "fileformats-bare"
Requires-Dist: fastexcel; extra == "fileformats-bare"
Requires-Dist: XlsxWriter; extra == "fileformats-bare"
Requires-Dist: stdf-tamer[fileformats_bare]; extra == "fileformats-lts"
Requires-Dist: polars-lts-cpu>=1.0.0; extra == "fileformats-lts"
Requires-Dist: stdf-tamer[fileformats_bare]; extra == "fileformats"
Requires-Dist: polars>=1.0.0; extra == "fileformats"
Requires-Dist: stdf-tamer[robotframework_bare]; extra == "robotframework-lts"
Requires-Dist: polars-lts-cpu; python_version >= "3.8" and extra == "robotframework-lts"
Requires-Dist: stdf-tamer[robotframework_bare]; extra == "robotframework"
Requires-Dist: polars; python_version >= "3.8" and extra == "robotframework"
Requires-Dist: pdoc>=0.4.1; python_version >= "3.8" and extra == "dev"
Requires-Dist: ipython>=7.16.3; python_version >= "3.8" and extra == "dev"
Requires-Dist: radon>=6.0.1; python_version >= "3.8" and extra == "dev"
Provides-Extra: robotframework-bare
Provides-Extra: fileformats-bare
Provides-Extra: fileformats-lts
Provides-Extra: fileformats
Provides-Extra: robotframework-lts
Provides-Extra: robotframework
Provides-Extra: dev
